eventstudio/__init__.py
eventstudio/constants.py
eventstudio/extension.py
eventstudio/api/__init__.py
eventstudio/api/common.py
eventstudio/api/config.py
eventstudio/api/event_storage.py
eventstudio/api/event_streamer.py
eventstudio/api/logging_handler.py
eventstudio/api/models.py
eventstudio/api/replay.py
eventstudio/api/web.py
eventstudio/api/types/__init__.py
eventstudio/api/types/errors.py
eventstudio/api/types/events.py
eventstudio/api/types/requests.py
eventstudio/api/types/responses.py
eventstudio/api/types/services.py
eventstudio/api/types/trace_context.py
eventstudio/api/utils/__init__.py
eventstudio/api/utils/arn_utils.py
eventstudio/api/utils/tracing_utils.py
eventstudio/api/utils/utils.py
eventstudio/api/utils/xray_tracing_utils.py
eventstudio/static/__init__.py
eventstudio/static/favicon.png
eventstudio/static/index-2QW6EDJI.js
eventstudio/static/index-2QW6EDJI.js.map
eventstudio/static/index-J5YJ3WIU.css
eventstudio/static/index-J5YJ3WIU.css.map
eventstudio/static/index-QFYNOU5N.js
eventstudio/static/index-QFYNOU5N.js.map
eventstudio/static/index-UUISF6VF.html
eventstudio/static/index-VNXTCUXW.js
eventstudio/static/index-VNXTCUXW.js.map
eventstudio/static/index-ZCXYKBRD.js
eventstudio/static/index-ZCXYKBRD.js.map
eventstudio/static/index.html
eventstudio/static/manifest.json
eventstudio/static/robots.txt
localstack_extension_event_studio-0.1.0.post2.dist-info/METADATA
localstack_extension_event_studio-0.1.0.post2.dist-info/WHEEL
localstack_extension_event_studio-0.1.0.post2.dist-info/entry_points.txt
localstack_extension_event_studio-0.1.0.post2.dist-info/top_level.txt
localstack_extension_event_studio-0.1.0.post2.dist-info/RECORD
