Metadata-Version: 2.1
Name: localstack-extension-event-studio
Version: 0.1.0.post2
Summary: LocalStack Extension: eventstudio
Author-email: Maximilian Hoheiser <max.hoheiser@gmail.com>
License: UNLICENSED
Project-URL: Homepage, https://github.com/localstack/localstack-extension-event-studio
Keywords: localstack,localstack-extension,extension
Requires-Python: >=3.11
Requires-Dist: rolo
Requires-Dist: boto3
Requires-Dist: sqlalchemy
Requires-Dist: jinja2
Requires-Dist: pydantic
Requires-Dist: python-dotenv
Provides-Extra: test
Requires-Dist: localstack-core>=3.3; extra == "test"
Requires-Dist: aws-cdk-lib; extra == "test"
Requires-Dist: ruff; extra == "test"
Requires-Dist: pytest; extra == "test"
Requires-Dist: pytest_httpserver; extra == "test"
Provides-Extra: dev
Requires-Dist: localstack-extension-event-studio[test]; extra == "dev"
Requires-Dist: airspeed-ext; extra == "dev"
Requires-Dist: amazon.ion; extra == "dev"
Requires-Dist: amazon_kclpy; extra == "dev"
Requires-Dist: apispec; extra == "dev"
Requires-Dist: aws-encryption-sdk; extra == "dev"
Requires-Dist: aws-sam-translator; extra == "dev"
Requires-Dist: awscli; extra == "dev"
Requires-Dist: awscrt; extra == "dev"
Requires-Dist: avro; extra == "dev"
Requires-Dist: crontab; extra == "dev"
Requires-Dist: boto3; extra == "dev"
Requires-Dist: botocore; extra == "dev"
Requires-Dist: cbor2; extra == "dev"
Requires-Dist: dirtyjson; extra == "dev"
Requires-Dist: dnspython; extra == "dev"
Requires-Dist: distro; extra == "dev"
Requires-Dist: docker; extra == "dev"
Requires-Dist: docker-registry-client; extra == "dev"
Requires-Dist: dulwich; extra == "dev"
Requires-Dist: graphql-core; extra == "dev"
Requires-Dist: hypercorn; extra == "dev"
Requires-Dist: janus; extra == "dev"
Requires-Dist: JPype1; extra == "dev"
Requires-Dist: json5; extra == "dev"
Requires-Dist: jsonpatch; extra == "dev"
Requires-Dist: jsonpath-ng; extra == "dev"
Requires-Dist: jsonpath-rw; extra == "dev"
Requires-Dist: Js2Py; extra == "dev"
Requires-Dist: kafka-python; extra == "dev"
Requires-Dist: kubernetes; extra == "dev"
Requires-Dist: libvirt-python; extra == "dev"
Requires-Dist: localstack-core; extra == "dev"
Requires-Dist: localstack-twisted; extra == "dev"
Requires-Dist: localstack_snapshot; extra == "dev"
Requires-Dist: moto-ext[all]; extra == "dev"
Requires-Dist: mysql-replication; extra == "dev"
Requires-Dist: opensearch-py; extra == "dev"
Requires-Dist: openapi_core; extra == "dev"
Requires-Dist: paho-mqtt; extra == "dev"
Requires-Dist: parquet; extra == "dev"
Requires-Dist: parse; extra == "dev"
Requires-Dist: pg8000; extra == "dev"
Requires-Dist: postgres; extra == "dev"
Requires-Dist: postgresql-proxy; extra == "dev"
Requires-Dist: pproxy-ext; extra == "dev"
Requires-Dist: presto-python-client; extra == "dev"
Requires-Dist: pycdlib; extra == "dev"
Requires-Dist: pyftpdlib; extra == "dev"
Requires-Dist: pyhive; extra == "dev"
Requires-Dist: pyion2json; extra == "dev"
Requires-Dist: PyJWT; extra == "dev"
Requires-Dist: pymongo; extra == "dev"
Requires-Dist: pymysql; extra == "dev"
Requires-Dist: pyopenssl; extra == "dev"
Requires-Dist: pyqldb; extra == "dev"
Requires-Dist: python-snappy; extra == "dev"
Requires-Dist: readerwriterlock; extra == "dev"
Requires-Dist: redis; extra == "dev"
Requires-Dist: requests-aws4auth; extra == "dev"
Requires-Dist: rolo; extra == "dev"
Requires-Dist: rsa; extra == "dev"
Requires-Dist: service_identity; extra == "dev"
Requires-Dist: sqlglot; extra == "dev"
Requires-Dist: sql-metadata; extra == "dev"
Requires-Dist: srp-ext; extra == "dev"
Requires-Dist: testing.common.database; extra == "dev"
Requires-Dist: thrift; extra == "dev"
Requires-Dist: thrift_sasl; extra == "dev"
Requires-Dist: tornado; extra == "dev"
Requires-Dist: urllib3; extra == "dev"
Requires-Dist: warrant-ext; extra == "dev"
Requires-Dist: websockets; extra == "dev"
Requires-Dist: Werkzeug; extra == "dev"
Requires-Dist: Whoosh; extra == "dev"
Requires-Dist: xmltodict; extra == "dev"
Requires-Dist: antlr4-python3-runtime; extra == "dev"
Requires-Dist: cryptography; extra == "dev"
Provides-Extra: package
Requires-Dist: localstack-core>=3.3; extra == "package"
Requires-Dist: localstack-ext>=3.3; extra == "package"
Requires-Dist: localstack-obfuscator>=0.3.0; extra == "package"
Requires-Dist: pyaes; extra == "package"
